
[
  {
    "userCount":"123@qq.com",
    "userName":"王明",
    "userType":"已注册未认证用户",
    "userState":"进行中",
    "userPhone":"1224324",
    "option":"启用 禁用 查看"
  },
  {
    "userCount":"123@qq.com",
    "userName":"王明",
    "userType":"已注册未认证用户",
    "userState":"进行中",
    "userPhone":"1224324",
    "option":"启用 禁用 查看"
  },{
  "userCount":"123@qq.com",
  "userName":"王明",
  "userType":"已注册未认证用户",
  "userState":"进行中",
  "userPhone":"1224324",
  "option":"启用 禁用 查看"
},{
  "userCount":"123@qq.com",
  "userName":"王明",
  "userType":"已注册未认证用户",
  "userState":"进行中",
  "userPhone":"1224324",
  "option":"启用 禁用 查看"
},{
  "userCount":"123@qq.com",
  "userName":"王明",
  "userType":"已注册未认证用户",
  "userState":"进行中",
  "userPhone":"1224324",
  "option":"启用 禁用 查看"
},{
  "userCount":"123@qq.com",
  "userName":"王明",
  "userType":"已注册未认证用户",
  "userState":"进行中",
  "userPhone":"1224324",
  "option":"启用 禁用 查看"
},{
  "userCount":"123@qq.com",
  "userName":"王明",
  "userType":"已注册未认证用户",
  "userState":"进行中",
  "userPhone":"1224324",
  "option":"启用 禁用 查看"
},{
  "userCount":"123@qq.com",
  "userName":"王明",
  "userType":"已注册未认证用户",
  "userState":"进行中",
  "userPhone":"1224324",
  "option":"启用 禁用 查看"
},{
  "userCount":"123@qq.com",
  "userName":"王明",
  "userType":"已注册未认证用户",
  "userState":"进行中",
  "userPhone":"1224324",
  "option":"启用 禁用 查看"
},{
  "userCount":"123@qq.com",
  "userName":"王明",
  "userType":"已注册未认证用户",
  "userState":"进行中",
  "userPhone":"1224324",
  "option":"启用 禁用 查看"
},{
  "userCount":"123@qq.com",
  "userName":"王明",
  "userType":"已注册未认证用户",
  "userState":"进行中",
  "userPhone":"1224324",
  "option":"启用 禁用 查看"
},{
  "userCount":"123@qq.com",
  "userName":"王明",
  "userType":"已注册未认证用户",
  "userState":"进行中",
  "userPhone":"1224324",
  "option":"启用 禁用 查看"
},{
  "userCount":"123@qq.com",
  "userName":"王明",
  "userType":"已注册未认证用户",
  "userState":"进行中",
  "userPhone":"1224324",
  "option":"启用 禁用 查看"
},{
  "userCount":"123@qq.com",
  "userName":"王明",
  "userType":"已注册未认证用户",
  "userState":"进行中",
  "userPhone":"1224324",
  "option":"启用 禁用 查看"
}
]
